pweb_ui/__init__.py
pweb_ui/pweb_ui_module.py
pweb_ui/common/__init__.py
pweb_ui/common/pweb_ui_config.py
pweb_ui/common/pweb_ui_helper.py
pweb_ui/common/pweb_ui_sys.py
pweb_ui/controller/__init__.py
pweb_ui/controller/auth_api_controller.py
pweb_ui/controller/auth_controller.py
pweb_ui/controller/operator_controller.py
pweb_ui/controller/pweb_ui_static_controller.py
pweb_ui/template-assets/assets/css/pui-admin-base.css
pweb_ui/template-assets/assets/css/pui-auth-base.css
pweb_ui/template-assets/assets/css/pui-footer.css
pweb_ui/template-assets/assets/css/lib/bootstrap.min.css
pweb_ui/template-assets/assets/img/default-img.jpg
pweb_ui/template-assets/assets/img/header-bg.png
pweb_ui/template-assets/assets/img/logo.png
pweb_ui/template-assets/assets/js/lib/bootstrap-form-validator.js
pweb_ui/template-assets/assets/js/lib/bootstrap.bundle.min.js
pweb_ui/template-assets/assets/js/lib/fontawesome-all.min.js
pweb_ui/template-assets/assets/js/lib/jquery-3.7.1.min.js
pweb_ui/template-assets/assets/js/lib/confirm/jquery-confirm.min.css
pweb_ui/template-assets/assets/js/lib/confirm/jquery-confirm.min.js
pweb_ui/template-assets/assets/js/lib/datepicker/popper.min.js
pweb_ui/template-assets/assets/js/lib/datepicker/tempus-dominus.min.css
pweb_ui/template-assets/assets/js/lib/datepicker/tempus-dominus.min.js
pweb_ui/template-assets/assets/js/lib/datepicker/tempus-jquery-provider.js
pweb_ui/template-assets/assets/js/lib/select2/select2-bootstrap-5-theme.min.css
pweb_ui/template-assets/assets/js/lib/select2/select2.min.css
pweb_ui/template-assets/assets/js/lib/select2/select2.min.js
pweb_ui/template-assets/assets/js/pweb/pweb.ajax.js
pweb_ui/template-assets/assets/js/pweb/pweb.init.js
pweb_ui/template-assets/assets/js/pweb/pweb.js
pweb_ui/template-assets/assets/js/pweb/pweb.message.box.js
pweb_ui/template-assets/templates/auth/forgot-password.html
pweb_ui/template-assets/templates/auth/forgot-response.html
pweb_ui/template-assets/templates/auth/login.html
pweb_ui-0.0.6.dist-info/LICENSE
pweb_ui-0.0.6.dist-info/METADATA
pweb_ui-0.0.6.dist-info/WHEEL
pweb_ui-0.0.6.dist-info/top_level.txt
pweb_ui-0.0.6.dist-info/RECORD
