Metadata-Version: 2.1
Name: pweb-ui
Version: 0.0.6
Summary: Its a starter of pweb, here will be basic authentication module, and rest system
Home-page: https://github.com/banglafighter/pweb-ui
Author: Bangla Fighter
Author-email: banglafighter.com@gmail.com
License: Apache 2.0
Platform: any
Classifier: Intended Audience :: Developers
Classifier: License :: OSI Approved :: Apache Software License
Classifier: Programming Language :: Python
License-File: LICENSE
